{"issues_url": "https://api.github.com/repos/ramda/ramda/issues{/number}", "deployments_url": "https://api.github.com/repos/ramda/ramda/deployments", "stargazers_count": 6127, "forks_url": "https://api.github.com/repos/ramda/ramda/forks", "mirror_url": null, "subscription_url": "https://api.github.com/repos/ramda/ramda/subscription", "notifications_url": "https://api.github.com/repos/ramda/ramda/notifications{?since,all,participating}", "collaborators_url": "https://api.github.com/repos/ramda/ramda/collaborators{/collaborator}", "updated_at": "2016-11-22T13:39:50Z", "private": false, "pulls_url": "https://api.github.com/repos/ramda/ramda/pulls{/number}", "issue_comment_url": "https://api.github.com/repos/ramda/ramda/issues/comments{/number}", "labels_url": "https://api.github.com/repos/ramda/ramda/labels{/name}", "has_wiki": true, "full_name": "ramda/ramda", "owner": {"following_url": "https://api.github.com/users/ramda/following{/other_user}", "events_url": "https://api.github.com/users/ramda/events{/privacy}", "organizations_url": "https://api.github.com/users/ramda/orgs", "url": "https://api.github.com/users/ramda", "gists_url": "https://api.github.com/users/ramda/gists{/gist_id}", "html_url": "https://github.com/ramda", "subscriptions_url": "https://api.github.com/users/ramda/subscriptions", "avatar_url": "https://avatars.githubusercontent.com/u/5298359?v=3", "repos_url": "https://api.github.com/users/ramda/repos", "received_events_url": "https://api.github.com/users/ramda/received_events", "gravatar_id": "", "starred_url": "https://api.github.com/users/ramda/starred{/owner}{/repo}", "site_admin": false, "login": "ramda", "type": "Organization", "id": 5298359, "followers_url": "https://api.github.com/users/ramda/followers"}, "statuses_url": "https://api.github.com/repos/ramda/ramda/statuses/{sha}", "id": 10851820, "keys_url": "https://api.github.com/repos/ramda/ramda/keys{/key_id}", "description": ":ram: Practical functional Javascript", "subscribers_count": 184, "tags_url": "https://api.github.com/repos/ramda/ramda/tags", "network_count": 410, "downloads_url": "https://api.github.com/repos/ramda/ramda/downloads", "assignees_url": "https://api.github.com/repos/ramda/ramda/assignees{/user}", "contents_url": "https://api.github.com/repos/ramda/ramda/contents/{+path}", "has_pages": false, "git_refs_url": "https://api.github.com/repos/ramda/ramda/git/refs{/sha}", "open_issues_count": 181, "clone_url": "https://github.com/ramda/ramda.git", "watchers_count": 6127, "git_tags_url": "https://api.github.com/repos/ramda/ramda/git/tags{/sha}", "milestones_url": "https://api.github.com/repos/ramda/ramda/milestones{/number}", "languages_url": "https://api.github.com/repos/ramda/ramda/languages", "size": 8015, "homepage": "http://ramdajs.com", "fork": false, "commits_url": "https://api.github.com/repos/ramda/ramda/commits{/sha}", "releases_url": "https://api.github.com/repos/ramda/ramda/releases{/id}", "issue_events_url": "https://api.github.com/repos/ramda/ramda/issues/events{/number}", "archive_url": "https://api.github.com/repos/ramda/ramda/{archive_format}{/ref}", "comments_url": "https://api.github.com/repos/ramda/ramda/comments{/number}", "events_url": "https://api.github.com/repos/ramda/ramda/events", "contributors_url": "https://api.github.com/repos/ramda/ramda/contributors", "html_url": "https://github.com/ramda/ramda", "forks": 410, "compare_url": "https://api.github.com/repos/ramda/ramda/compare/{base}...{head}", "open_issues": 181, "git_url": "git://github.com/ramda/ramda.git", "svn_url": "https://github.com/ramda/ramda", "merges_url": "https://api.github.com/repos/ramda/ramda/merges", "has_issues": true, "ssh_url": "git@github.com:ramda/ramda.git", "blobs_url": "https://api.github.com/repos/ramda/ramda/git/blobs{/sha}", "git_commits_url": "https://api.github.com/repos/ramda/ramda/git/commits{/sha}", "hooks_url": "https://api.github.com/repos/ramda/ramda/hooks", "has_downloads": true, "watchers": 6127, "name": "ramda", "language": "JavaScript", "url": "https://api.github.com/repos/ramda/ramda", "created_at": "2013-06-21T20:32:35Z", "pushed_at": "2016-11-21T15:20:54Z", "forks_count": 410, "default_branch": "master", "teams_url": "https://api.github.com/repos/ramda/ramda/teams", "trees_url": "https://api.github.com/repos/ramda/ramda/git/trees{/sha}", "organization": {"following_url": "https://api.github.com/users/ramda/following{/other_user}", "events_url": "https://api.github.com/users/ramda/events{/privacy}", "organizations_url": "https://api.github.com/users/ramda/orgs", "url": "https://api.github.com/users/ramda", "gists_url": "https://api.github.com/users/ramda/gists{/gist_id}", "html_url": "https://github.com/ramda", "subscriptions_url": "https://api.github.com/users/ramda/subscriptions", "avatar_url": "https://avatars.githubusercontent.com/u/5298359?v=3", "repos_url": "https://api.github.com/users/ramda/repos", "received_events_url": "https://api.github.com/users/ramda/received_events", "gravatar_id": "", "starred_url": "https://api.github.com/users/ramda/starred{/owner}{/repo}", "site_admin": false, "login": "ramda", "type": "Organization", "id": 5298359, "followers_url": "https://api.github.com/users/ramda/followers"}, "branches_url": "https://api.github.com/repos/ramda/ramda/branches{/branch}", "subscribers_url": "https://api.github.com/repos/ramda/ramda/subscribers", "permissions": {"admin": false, "push": false, "pull": true}, "stargazers_url": "https://api.github.com/repos/ramda/ramda/stargazers"}