{"deployments_url": "https://api.github.com/repos/Kickball/awesome-selfhosted/deployments", "has_wiki": true, "forks_url": "https://api.github.com/repos/Kickball/awesome-selfhosted/forks", "mirror_url": null, "subscription_url": "https://api.github.com/repos/Kickball/awesome-selfhosted/subscription", "notifications_url": "https://api.github.com/repos/Kickball/awesome-selfhosted/notifications{?since,all,participating}", "subscribers_count": 627, "updated_at": "2016-11-22T20:45:45Z", "svn_url": "https://github.com/Kickball/awesome-selfhosted", "pulls_url": "https://api.github.com/repos/Kickball/awesome-selfhosted/pulls{/number}", "issue_comment_url": "https://api.github.com/repos/Kickball/awesome-selfhosted/issues/comments{/number}", "full_name": "Kickball/awesome-selfhosted", "owner": {"following_url": "https://api.github.com/users/Kickball/following{/other_user}", "events_url": "https://api.github.com/users/Kickball/events{/privacy}", "organizations_url": "https://api.github.com/users/Kickball/orgs", "url": "https://api.github.com/users/Kickball", "gists_url": "https://api.github.com/users/Kickball/gists{/gist_id}", "html_url": "https://github.com/Kickball", "subscriptions_url": "https://api.github.com/users/Kickball/subscriptions", "avatar_url": "https://avatars.githubusercontent.com/u/2252004?v=3", "repos_url": "https://api.github.com/users/Kickball/repos", "received_events_url": "https://api.github.com/users/Kickball/received_events", "gravatar_id": "", "starred_url": "https://api.github.com/users/Kickball/starred{/owner}{/repo}", "site_admin": false, "login": "Kickball", "type": "User", "id": 2252004, "followers_url": "https://api.github.com/users/Kickball/followers"}, "contents_url": "https://api.github.com/repos/Kickball/awesome-selfhosted/contents/{+path}", "id": 36633370, "keys_url": "https://api.github.com/repos/Kickball/awesome-selfhosted/keys{/key_id}", "size": 3628, "network_count": 949, "downloads_url": "https://api.github.com/repos/Kickball/awesome-selfhosted/downloads", "assignees_url": "https://api.github.com/repos/Kickball/awesome-selfhosted/assignees{/user}", "statuses_url": "https://api.github.com/repos/Kickball/awesome-selfhosted/statuses/{sha}", "description": "This is a list of Free Software network services and web applications which can be hosted locally. Selfhosting is the process of locally hosting and managing applications instead of renting from SaaS providers.", "git_refs_url": "https://api.github.com/repos/Kickball/awesome-selfhosted/git/refs{/sha}", "clone_url": "https://github.com/Kickball/awesome-selfhosted.git", "watchers_count": 12863, "git_tags_url": "https://api.github.com/repos/Kickball/awesome-selfhosted/git/tags{/sha}", "milestones_url": "https://api.github.com/repos/Kickball/awesome-selfhosted/milestones{/number}", "stargazers_count": 12863, "hooks_url": "https://api.github.com/repos/Kickball/awesome-selfhosted/hooks", "homepage": "https://reddit.com/r/selfhosted", "open_issues": 33, "fork": false, "commits_url": "https://api.github.com/repos/Kickball/awesome-selfhosted/commits{/sha}", "releases_url": "https://api.github.com/repos/Kickball/awesome-selfhosted/releases{/id}", "issue_events_url": "https://api.github.com/repos/Kickball/awesome-selfhosted/issues/events{/number}", "has_downloads": true, "has_pages": false, "events_url": "https://api.github.com/repos/Kickball/awesome-selfhosted/events", "default_branch": "master", "html_url": "https://github.com/Kickball/awesome-selfhosted", "languages_count": 1, "compare_url": "https://api.github.com/repos/Kickball/awesome-selfhosted/compare/{base}...{head}", "language": "Makefile", "contributors_count": 263, "private": false, "forks_count": 949, "merges_url": "https://api.github.com/repos/Kickball/awesome-selfhosted/merges", "has_issues": true, "ssh_url": "git@github.com:Kickball/awesome-selfhosted.git", "blobs_url": "https://api.github.com/repos/Kickball/awesome-selfhosted/git/blobs{/sha}", "forks": 949, "permissions": {"admin": false, "push": false, "pull": true}, "issues_count": 31, "labels_count": 7, "open_issues_count": 33, "watchers": 12863, "name": "awesome-selfhosted", "branches_count": 5, "url": "https://api.github.com/repos/Kickball/awesome-selfhosted", "created_at": "2015-06-01T02:33:17Z", "archive_url": "https://api.github.com/repos/Kickball/awesome-selfhosted/{archive_format}{/ref}", "pushed_at": "2016-11-22T21:17:59Z", "collaborators_url": "https://api.github.com/repos/Kickball/awesome-selfhosted/collaborators{/collaborator}", "teams_url": "https://api.github.com/repos/Kickball/awesome-selfhosted/teams", "tags_count": 0, "trees_url": "https://api.github.com/repos/Kickball/awesome-selfhosted/git/trees{/sha}", "git_commits_url": "https://api.github.com/repos/Kickball/awesome-selfhosted/git/commits{/sha}", "subscribers_url": "https://api.github.com/repos/Kickball/awesome-selfhosted/subscribers", "comments_url": "https://api.github.com/repos/Kickball/awesome-selfhosted/comments{/number}", "stargazers_url": "https://api.github.com/repos/Kickball/awesome-selfhosted/stargazers", "git_url": "git://github.com/Kickball/awesome-selfhosted.git"}