{"deployments_url": "https://api.github.com/repos/lodash-archive/lodash-fp/deployments", "has_wiki": false, "forks_url": "https://api.github.com/repos/lodash-archive/lodash-fp/forks", "mirror_url": null, "stargazers_count": 498, "subscription_url": "https://api.github.com/repos/lodash-archive/lodash-fp/subscription", "notifications_url": "https://api.github.com/repos/lodash-archive/lodash-fp/notifications{?since,all,participating}", "subscribers_count": 30, "updated_at": "2016-11-17T14:23:28Z", "svn_url": "https://github.com/lodash-archive/lodash-fp", "pulls_url": "https://api.github.com/repos/lodash-archive/lodash-fp/pulls{/number}", "issue_comment_url": "https://api.github.com/repos/lodash-archive/lodash-fp/issues/comments{/number}", "full_name": "lodash-archive/lodash-fp", "owner": {"following_url": "https://api.github.com/users/lodash-archive/following{/other_user}", "events_url": "https://api.github.com/users/lodash-archive/events{/privacy}", "organizations_url": "https://api.github.com/users/lodash-archive/orgs", "url": "https://api.github.com/users/lodash-archive", "gists_url": "https://api.github.com/users/lodash-archive/gists{/gist_id}", "html_url": "https://github.com/lodash-archive", "subscriptions_url": "https://api.github.com/users/lodash-archive/subscriptions", "avatar_url": "https://avatars.githubusercontent.com/u/16309616?v=3", "repos_url": "https://api.github.com/users/lodash-archive/repos", "received_events_url": "https://api.github.com/users/lodash-archive/received_events", "gravatar_id": "", "starred_url": "https://api.github.com/users/lodash-archive/starred{/owner}{/repo}", "site_admin": false, "login": "lodash-archive", "type": "Organization", "id": 16309616, "followers_url": "https://api.github.com/users/lodash-archive/followers"}, "contents_url": "https://api.github.com/repos/lodash-archive/lodash-fp/contents/{+path}", "id": 29086069, "keys_url": "https://api.github.com/repos/lodash-archive/lodash-fp/keys{/key_id}", "size": 473, "network_count": 11, "downloads_url": "https://api.github.com/repos/lodash-archive/lodash-fp/downloads", "assignees_url": "https://api.github.com/repos/lodash-archive/lodash-fp/assignees{/user}", "statuses_url": "https://api.github.com/repos/lodash-archive/lodash-fp/statuses/{sha}", "description": "Lodash with more functional fun.", "git_refs_url": "https://api.github.com/repos/lodash-archive/lodash-fp/git/refs{/sha}", "clone_url": "https://github.com/lodash-archive/lodash-fp.git", "watchers_count": 498, "git_tags_url": "https://api.github.com/repos/lodash-archive/lodash-fp/git/tags{/sha}", "milestones_url": "https://api.github.com/repos/lodash-archive/lodash-fp/milestones{/number}", "hooks_url": "https://api.github.com/repos/lodash-archive/lodash-fp/hooks", "homepage": "", "open_issues": 1, "fork": false, "commits_url": "https://api.github.com/repos/lodash-archive/lodash-fp/commits{/sha}", "releases_url": "https://api.github.com/repos/lodash-archive/lodash-fp/releases{/id}", "issue_events_url": "https://api.github.com/repos/lodash-archive/lodash-fp/issues/events{/number}", "has_downloads": true, "has_pages": false, "events_url": "https://api.github.com/repos/lodash-archive/lodash-fp/events", "default_branch": "master", "html_url": "https://github.com/lodash-archive/lodash-fp", "languages_count": 1, "compare_url": "https://api.github.com/repos/lodash-archive/lodash-fp/compare/{base}...{head}", "language": "JavaScript", "contributors_count": 1, "private": false, "forks_count": 11, "merges_url": "https://api.github.com/repos/lodash-archive/lodash-fp/merges", "has_issues": false, "ssh_url": "git@github.com:lodash-archive/lodash-fp.git", "blobs_url": "https://api.github.com/repos/lodash-archive/lodash-fp/git/blobs{/sha}", "forks": 11, "permissions": {"admin": false, "push": false, "pull": true}, "issues_count": 0, "labels_count": 11, "open_issues_count": 1, "watchers": 498, "name": "lodash-fp", "branches_count": 1, "url": "https://api.github.com/repos/lodash-archive/lodash-fp", "created_at": "2015-01-11T08:41:17Z", "archive_url": "https://api.github.com/repos/lodash-archive/lodash-fp/{archive_format}{/ref}", "pushed_at": "2016-03-06T01:30:38Z", "collaborators_url": "https://api.github.com/repos/lodash-archive/lodash-fp/collaborators{/collaborator}", "teams_url": "https://api.github.com/repos/lodash-archive/lodash-fp/teams", "tags_count": 19, "trees_url": "https://api.github.com/repos/lodash-archive/lodash-fp/git/trees{/sha}", "organization": {"following_url": "https://api.github.com/users/lodash-archive/following{/other_user}", "events_url": "https://api.github.com/users/lodash-archive/events{/privacy}", "organizations_url": "https://api.github.com/users/lodash-archive/orgs", "url": "https://api.github.com/users/lodash-archive", "gists_url": "https://api.github.com/users/lodash-archive/gists{/gist_id}", "html_url": "https://github.com/lodash-archive", "subscriptions_url": "https://api.github.com/users/lodash-archive/subscriptions", "avatar_url": "https://avatars.githubusercontent.com/u/16309616?v=3", "repos_url": "https://api.github.com/users/lodash-archive/repos", "received_events_url": "https://api.github.com/users/lodash-archive/received_events", "gravatar_id": "", "starred_url": "https://api.github.com/users/lodash-archive/starred{/owner}{/repo}", "site_admin": false, "login": "lodash-archive", "type": "Organization", "id": 16309616, "followers_url": "https://api.github.com/users/lodash-archive/followers"}, "git_commits_url": "https://api.github.com/repos/lodash-archive/lodash-fp/git/commits{/sha}", "subscribers_url": "https://api.github.com/repos/lodash-archive/lodash-fp/subscribers", "comments_url": "https://api.github.com/repos/lodash-archive/lodash-fp/comments{/number}", "stargazers_url": "https://api.github.com/repos/lodash-archive/lodash-fp/stargazers", "git_url": "git://github.com/lodash-archive/lodash-fp.git"}