{"deployments_url": "https://api.github.com/repos/handsontable/docs/deployments", "has_wiki": true, "forks_url": "https://api.github.com/repos/handsontable/docs/forks", "mirror_url": null, "subscription_url": "https://api.github.com/repos/handsontable/docs/subscription", "merges_url": "https://api.github.com/repos/handsontable/docs/merges", "subscribers_count": 15, "updated_at": "2016-07-29T06:13:34Z", "svn_url": "https://github.com/handsontable/docs", "pulls_url": "https://api.github.com/repos/handsontable/docs/pulls{/number}", "issue_comment_url": "https://api.github.com/repos/handsontable/docs/issues/comments{/number}", "git_url": "git://github.com/handsontable/docs.git", "full_name": "handsontable/docs", "owner": {"following_url": "https://api.github.com/users/handsontable/following{/other_user}", "gists_url": "https://api.github.com/users/handsontable/gists{/gist_id}", "organizations_url": "https://api.github.com/users/handsontable/orgs", "url": "https://api.github.com/users/handsontable", "events_url": "https://api.github.com/users/handsontable/events{/privacy}", "html_url": "https://github.com/handsontable", "subscriptions_url": "https://api.github.com/users/handsontable/subscriptions", "avatar_url": "https://avatars.githubusercontent.com/u/8068250?v=3", "repos_url": "https://api.github.com/users/handsontable/repos", "received_events_url": "https://api.github.com/users/handsontable/received_events", "gravatar_id": "", "starred_url": "https://api.github.com/users/handsontable/starred{/owner}{/repo}", "site_admin": false, "login": "handsontable", "type": "Organization", "id": 8068250, "followers_url": "https://api.github.com/users/handsontable/followers"}, "branches_count": 37, "contents_url": "https://api.github.com/repos/handsontable/docs/contents/{+path}", "id": 28106368, "keys_url": "https://api.github.com/repos/handsontable/docs/keys{/key_id}", "size": 5764, "issue_events_url": "https://api.github.com/repos/handsontable/docs/issues/events{/number}", "network_count": 383, "downloads_url": "https://api.github.com/repos/handsontable/docs/downloads", "assignees_url": "https://api.github.com/repos/handsontable/docs/assignees{/user}", "statuses_url": "https://api.github.com/repos/handsontable/docs/statuses/{sha}", "has_pages": false, "git_refs_url": "https://api.github.com/repos/handsontable/docs/git/refs{/sha}", "languages": {}, "clone_url": "https://github.com/handsontable/docs.git", "watchers_count": 2, "git_tags_url": "https://api.github.com/repos/handsontable/docs/git/tags{/sha}", "stargazers_count": 2, "permissions": {"admin": false, "push": false, "pull": true}, "homepage": null, "fork": false, "releases_url": "https://api.github.com/repos/handsontable/docs/releases{/id}", "description": "API Documentation for Handsontable", "has_downloads": true, "milestones_url": "https://api.github.com/repos/handsontable/docs/milestones{/number}", "events_url": "https://api.github.com/repos/handsontable/docs/events", "default_branch": "develop", "html_url": "https://github.com/handsontable/docs", "languages_count": 0, "compare_url": "https://api.github.com/repos/handsontable/docs/compare/{base}...{head}", "trees_url": "https://api.github.com/repos/handsontable/docs/git/trees{/sha}", "contributors_count": 4, "private": false, "forks_count": 383, "notifications_url": "https://api.github.com/repos/handsontable/docs/notifications{?since,all,participating}", "has_issues": true, "ssh_url": "git@github.com:handsontable/docs.git", "blobs_url": "https://api.github.com/repos/handsontable/docs/git/blobs{/sha}", "forks": 383, "hooks_url": "https://api.github.com/repos/handsontable/docs/hooks", "issues_count": 11, "labels_count": 9, "open_issues_count": 11, "watchers": 2, "name": "docs", "language": null, "url": "https://api.github.com/repos/handsontable/docs", "created_at": "2014-12-16T20:58:34Z", "archive_url": "https://api.github.com/repos/handsontable/docs/{archive_format}{/ref}", "pushed_at": "2016-12-13T10:20:48Z", "collaborators_url": "https://api.github.com/repos/handsontable/docs/collaborators{/collaborator}", "comments_count": 0, "teams_url": "https://api.github.com/repos/handsontable/docs/teams", "tags_count": 0, "open_issues": 11, "organization": {"following_url": "https://api.github.com/users/handsontable/following{/other_user}", "gists_url": "https://api.github.com/users/handsontable/gists{/gist_id}", "organizations_url": "https://api.github.com/users/handsontable/orgs", "url": "https://api.github.com/users/handsontable", "events_url": "https://api.github.com/users/handsontable/events{/privacy}", "html_url": "https://github.com/handsontable", "subscriptions_url": "https://api.github.com/users/handsontable/subscriptions", "avatar_url": "https://avatars.githubusercontent.com/u/8068250?v=3", "repos_url": "https://api.github.com/users/handsontable/repos", "received_events_url": "https://api.github.com/users/handsontable/received_events", "gravatar_id": "", "starred_url": "https://api.github.com/users/handsontable/starred{/owner}{/repo}", "site_admin": false, "login": "handsontable", "type": "Organization", "id": 8068250, "followers_url": "https://api.github.com/users/handsontable/followers"}, "git_commits_url": "https://api.github.com/repos/handsontable/docs/git/commits{/sha}", "subscribers_url": "https://api.github.com/repos/handsontable/docs/subscribers", "stargazers_url": "https://api.github.com/repos/handsontable/docs/stargazers", "commits_count": 111}