{"deployments_url": "https://api.github.com/repos/sf-wdi-15/auth_homework/deployments", "has_wiki": true, "forks_url": "https://api.github.com/repos/sf-wdi-15/auth_homework/forks", "mirror_url": null, "subscription_url": "https://api.github.com/repos/sf-wdi-15/auth_homework/subscription", "merges_url": "https://api.github.com/repos/sf-wdi-15/auth_homework/merges", "subscribers_count": 2, "updated_at": "2014-12-09T23:52:36Z", "svn_url": "https://github.com/sf-wdi-15/auth_homework", "pulls_url": "https://api.github.com/repos/sf-wdi-15/auth_homework/pulls{/number}", "issue_comment_url": "https://api.github.com/repos/sf-wdi-15/auth_homework/issues/comments{/number}", "git_url": "git://github.com/sf-wdi-15/auth_homework.git", "full_name": "sf-wdi-15/auth_homework", "owner": {"following_url": "https://api.github.com/users/sf-wdi-15/following{/other_user}", "gists_url": "https://api.github.com/users/sf-wdi-15/gists{/gist_id}", "organizations_url": "https://api.github.com/users/sf-wdi-15/orgs", "url": "https://api.github.com/users/sf-wdi-15", "events_url": "https://api.github.com/users/sf-wdi-15/events{/privacy}", "html_url": "https://github.com/sf-wdi-15", "subscriptions_url": "https://api.github.com/users/sf-wdi-15/subscriptions", "avatar_url": "https://avatars.githubusercontent.com/u/9560583?v=3", "repos_url": "https://api.github.com/users/sf-wdi-15/repos", "received_events_url": "https://api.github.com/users/sf-wdi-15/received_events", "gravatar_id": "", "starred_url": "https://api.github.com/users/sf-wdi-15/starred{/owner}{/repo}", "site_admin": false, "login": "sf-wdi-15", "type": "Organization", "id": 9560583, "followers_url": "https://api.github.com/users/sf-wdi-15/followers"}, "branches_count": 1, "contents_url": "https://api.github.com/repos/sf-wdi-15/auth_homework/contents/{+path}", "id": 27793369, "keys_url": "https://api.github.com/repos/sf-wdi-15/auth_homework/keys{/key_id}", "size": 1708, "issue_events_url": "https://api.github.com/repos/sf-wdi-15/auth_homework/issues/events{/number}", "network_count": 12, "downloads_url": "https://api.github.com/repos/sf-wdi-15/auth_homework/downloads", "assignees_url": "https://api.github.com/repos/sf-wdi-15/auth_homework/assignees{/user}", "statuses_url": "https://api.github.com/repos/sf-wdi-15/auth_homework/statuses/{sha}", "has_pages": false, "git_refs_url": "https://api.github.com/repos/sf-wdi-15/auth_homework/git/refs{/sha}", "languages": {}, "clone_url": "https://github.com/sf-wdi-15/auth_homework.git", "watchers_count": 0, "git_tags_url": "https://api.github.com/repos/sf-wdi-15/auth_homework/git/tags{/sha}", "stargazers_count": 0, "permissions": {"admin": false, "push": false, "pull": true}, "homepage": null, "fork": false, "releases_url": "https://api.github.com/repos/sf-wdi-15/auth_homework/releases{/id}", "description": null, "has_downloads": true, "milestones_url": "https://api.github.com/repos/sf-wdi-15/auth_homework/milestones{/number}", "events_url": "https://api.github.com/repos/sf-wdi-15/auth_homework/events", "default_branch": "master", "html_url": "https://github.com/sf-wdi-15/auth_homework", "languages_count": 0, "compare_url": "https://api.github.com/repos/sf-wdi-15/auth_homework/compare/{base}...{head}", "trees_url": "https://api.github.com/repos/sf-wdi-15/auth_homework/git/trees{/sha}", "contributors_count": 1, "private": false, "forks_count": 12, "notifications_url": "https://api.github.com/repos/sf-wdi-15/auth_homework/notifications{?since,all,participating}", "has_issues": true, "ssh_url": "git@github.com:sf-wdi-15/auth_homework.git", "blobs_url": "https://api.github.com/repos/sf-wdi-15/auth_homework/git/blobs{/sha}", "forks": 12, "hooks_url": "https://api.github.com/repos/sf-wdi-15/auth_homework/hooks", "issues_count": 2, "labels_count": 7, "open_issues_count": 2, "watchers": 0, "name": "auth_homework", "language": null, "url": "https://api.github.com/repos/sf-wdi-15/auth_homework", "created_at": "2014-12-09T23:52:36Z", "archive_url": "https://api.github.com/repos/sf-wdi-15/auth_homework/{archive_format}{/ref}", "pushed_at": "2014-12-10T00:05:00Z", "collaborators_url": "https://api.github.com/repos/sf-wdi-15/auth_homework/collaborators{/collaborator}", "comments_count": 0, "teams_url": "https://api.github.com/repos/sf-wdi-15/auth_homework/teams", "tags_count": 0, "open_issues": 2, "organization": {"following_url": "https://api.github.com/users/sf-wdi-15/following{/other_user}", "gists_url": "https://api.github.com/users/sf-wdi-15/gists{/gist_id}", "organizations_url": "https://api.github.com/users/sf-wdi-15/orgs", "url": "https://api.github.com/users/sf-wdi-15", "events_url": "https://api.github.com/users/sf-wdi-15/events{/privacy}", "html_url": "https://github.com/sf-wdi-15", "subscriptions_url": "https://api.github.com/users/sf-wdi-15/subscriptions", "avatar_url": "https://avatars.githubusercontent.com/u/9560583?v=3", "repos_url": "https://api.github.com/users/sf-wdi-15/repos", "received_events_url": "https://api.github.com/users/sf-wdi-15/received_events", "gravatar_id": "", "starred_url": "https://api.github.com/users/sf-wdi-15/starred{/owner}{/repo}", "site_admin": false, "login": "sf-wdi-15", "type": "Organization", "id": 9560583, "followers_url": "https://api.github.com/users/sf-wdi-15/followers"}, "git_commits_url": "https://api.github.com/repos/sf-wdi-15/auth_homework/git/commits{/sha}", "subscribers_url": "https://api.github.com/repos/sf-wdi-15/auth_homework/subscribers", "stargazers_url": "https://api.github.com/repos/sf-wdi-15/auth_homework/stargazers", "commits_count": 3}