{"first_commit": {"committer": {"following_url": "https://api.github.com/users/diafygi/following{/other_user}", "events_url": "https://api.github.com/users/diafygi/events{/privacy}", "organizations_url": "https://api.github.com/users/diafygi/orgs", "url": "https://api.github.com/users/diafygi", "gists_url": "https://api.github.com/users/diafygi/gists{/gist_id}", "html_url": "https://github.com/diafygi", "subscriptions_url": "https://api.github.com/users/diafygi/subscriptions", "avatar_url": "https://avatars.githubusercontent.com/u/643187?v=3", "repos_url": "https://api.github.com/users/diafygi/repos", "received_events_url": "https://api.github.com/users/diafygi/received_events", "gravatar_id": "", "starred_url": "https://api.github.com/users/diafygi/starred{/owner}{/repo}", "site_admin": false, "login": "diafygi", "type": "User", "id": 643187, "followers_url": "https://api.github.com/users/diafygi/followers"}, "author": {"following_url": "https://api.github.com/users/diafygi/following{/other_user}", "events_url": "https://api.github.com/users/diafygi/events{/privacy}", "organizations_url": "https://api.github.com/users/diafygi/orgs", "url": "https://api.github.com/users/diafygi", "gists_url": "https://api.github.com/users/diafygi/gists{/gist_id}", "html_url": "https://github.com/diafygi", "subscriptions_url": "https://api.github.com/users/diafygi/subscriptions", "avatar_url": "https://avatars.githubusercontent.com/u/643187?v=3", "repos_url": "https://api.github.com/users/diafygi/repos", "received_events_url": "https://api.github.com/users/diafygi/received_events", "gravatar_id": "", "starred_url": "https://api.github.com/users/diafygi/starred{/owner}{/repo}", "site_admin": false, "login": "diafygi", "type": "User", "id": 643187, "followers_url": "https://api.github.com/users/diafygi/followers"}, "url": "https://api.github.com/repos/diafygi/webrtc-ips/commits/ba63ef512c5f4bb0ac798679bef5cab9b71efc4f", "comments_url": "https://api.github.com/repos/diafygi/webrtc-ips/commits/ba63ef512c5f4bb0ac798679bef5cab9b71efc4f/comments", "html_url": "https://github.com/diafygi/webrtc-ips/commit/ba63ef512c5f4bb0ac798679bef5cab9b71efc4f", "sha": "ba63ef512c5f4bb0ac798679bef5cab9b71efc4f", "parents": [{"url": "https://api.github.com/repos/diafygi/webrtc-ips/commits/9b890464b8c53d7fb6d11d736d940cb53c2b3856", "sha": "9b890464b8c53d7fb6d11d736d940cb53c2b3856", "html_url": "https://github.com/diafygi/webrtc-ips/commit/9b890464b8c53d7fb6d11d736d940cb53c2b3856"}, {"url": "https://api.github.com/repos/diafygi/webrtc-ips/commits/a95b3613e3ee83d2d51cfb184d334767cf71e486", "sha": "a95b3613e3ee83d2d51cfb184d334767cf71e486", "html_url": "https://github.com/diafygi/webrtc-ips/commit/a95b3613e3ee83d2d51cfb184d334767cf71e486"}], "commit": {"committer": {"date": "2015-07-20T20:52:44Z", "name": "Daniel Roesler", "email": "diafygi@gmail.com"}, "author": {"date": "2015-07-20T20:52:44Z", "name": "Daniel Roesler", "email": "diafygi@gmail.com"}, "url": "https://api.github.com/repos/diafygi/webrtc-ips/git/commits/ba63ef512c5f4bb0ac798679bef5cab9b71efc4f", "tree": {"url": "https://api.github.com/repos/diafygi/webrtc-ips/git/trees/c723ac1feb336564dd0705ed8105e912de0cb8c3", "sha": "c723ac1feb336564dd0705ed8105e912de0cb8c3"}, "comment_count": 0, "message": "Merge pull request #18 from KwadroNaut/master\n\nFirefox 41 disables the default (unreliable) STUN server"}}, "last_commit": {"committer": {"following_url": "https://api.github.com/users/diafygi/following{/other_user}", "events_url": "https://api.github.com/users/diafygi/events{/privacy}", "organizations_url": "https://api.github.com/users/diafygi/orgs", "url": "https://api.github.com/users/diafygi", "gists_url": "https://api.github.com/users/diafygi/gists{/gist_id}", "html_url": "https://github.com/diafygi", "subscriptions_url": "https://api.github.com/users/diafygi/subscriptions", "avatar_url": "https://avatars.githubusercontent.com/u/643187?v=3", "repos_url": "https://api.github.com/users/diafygi/repos", "received_events_url": "https://api.github.com/users/diafygi/received_events", "gravatar_id": "", "starred_url": "https://api.github.com/users/diafygi/starred{/owner}{/repo}", "site_admin": false, "login": "diafygi", "type": "User", "id": 643187, "followers_url": "https://api.github.com/users/diafygi/followers"}, "author": {"following_url": "https://api.github.com/users/diafygi/following{/other_user}", "events_url": "https://api.github.com/users/diafygi/events{/privacy}", "organizations_url": "https://api.github.com/users/diafygi/orgs", "url": "https://api.github.com/users/diafygi", "gists_url": "https://api.github.com/users/diafygi/gists{/gist_id}", "html_url": "https://github.com/diafygi", "subscriptions_url": "https://api.github.com/users/diafygi/subscriptions", "avatar_url": "https://avatars.githubusercontent.com/u/643187?v=3", "repos_url": "https://api.github.com/users/diafygi/repos", "received_events_url": "https://api.github.com/users/diafygi/received_events", "gravatar_id": "", "starred_url": "https://api.github.com/users/diafygi/starred{/owner}{/repo}", "site_admin": false, "login": "diafygi", "type": "User", "id": 643187, "followers_url": "https://api.github.com/users/diafygi/followers"}, "url": "https://api.github.com/repos/diafygi/webrtc-ips/commits/522366a65399ffc97c33d947593749947e8544f0", "comments_url": "https://api.github.com/repos/diafygi/webrtc-ips/commits/522366a65399ffc97c33d947593749947e8544f0/comments", "html_url": "https://github.com/diafygi/webrtc-ips/commit/522366a65399ffc97c33d947593749947e8544f0", "sha": "522366a65399ffc97c33d947593749947e8544f0", "parents": [], "commit": {"committer": {"date": "2015-01-26T05:55:12Z", "name": "Daniel Roesler", "email": "diafygi@gmail.com"}, "author": {"date": "2015-01-26T05:55:12Z", "name": "Daniel Roesler", "email": "diafygi@gmail.com"}, "url": "https://api.github.com/repos/diafygi/webrtc-ips/git/commits/522366a65399ffc97c33d947593749947e8544f0", "tree": {"url": "https://api.github.com/repos/diafygi/webrtc-ips/git/trees/195e7c51ee5c1668c3ccd3da5ed2847da2a74e23", "sha": "195e7c51ee5c1668c3ccd3da5ed2847da2a74e23"}, "comment_count": 0, "message": "Initial commit"}}, "commits_count": 12}