{"first_commit": {"committer": {"following_url": "https://api.github.com/users/sideshowbarker/following{/other_user}", "events_url": "https://api.github.com/users/sideshowbarker/events{/privacy}", "organizations_url": "https://api.github.com/users/sideshowbarker/orgs", "url": "https://api.github.com/users/sideshowbarker", "gists_url": "https://api.github.com/users/sideshowbarker/gists{/gist_id}", "html_url": "https://github.com/sideshowbarker", "subscriptions_url": "https://api.github.com/users/sideshowbarker/subscriptions", "avatar_url": "https://avatars.githubusercontent.com/u/194984?v=3", "repos_url": "https://api.github.com/users/sideshowbarker/repos", "received_events_url": "https://api.github.com/users/sideshowbarker/received_events", "gravatar_id": "", "starred_url": "https://api.github.com/users/sideshowbarker/starred{/owner}{/repo}", "site_admin": false, "login": "sideshowbarker", "type": "User", "id": 194984, "followers_url": "https://api.github.com/users/sideshowbarker/followers"}, "author": {"following_url": "https://api.github.com/users/bakkot/following{/other_user}", "events_url": "https://api.github.com/users/bakkot/events{/privacy}", "organizations_url": "https://api.github.com/users/bakkot/orgs", "url": "https://api.github.com/users/bakkot", "gists_url": "https://api.github.com/users/bakkot/gists{/gist_id}", "html_url": "https://github.com/bakkot", "subscriptions_url": "https://api.github.com/users/bakkot/subscriptions", "avatar_url": "https://avatars.githubusercontent.com/u/1653598?v=3", "repos_url": "https://api.github.com/users/bakkot/repos", "received_events_url": "https://api.github.com/users/bakkot/received_events", "gravatar_id": "", "starred_url": "https://api.github.com/users/bakkot/starred{/owner}{/repo}", "site_admin": false, "login": "bakkot", "type": "User", "id": 1653598, "followers_url": "https://api.github.com/users/bakkot/followers"}, "url": "https://api.github.com/repos/es6/es6.github.io/commits/14fd4a7f2e7e13605d30aa1f6139eac27f76d98e", "comments_url": "https://api.github.com/repos/es6/es6.github.io/commits/14fd4a7f2e7e13605d30aa1f6139eac27f76d98e/comments", "html_url": "https://github.com/es6/es6.github.io/commit/14fd4a7f2e7e13605d30aa1f6139eac27f76d98e", "sha": "14fd4a7f2e7e13605d30aa1f6139eac27f76d98e", "parents": [{"url": "https://api.github.com/repos/es6/es6.github.io/commits/410d1954b3319a335592793cb83a738af412fef4", "sha": "410d1954b3319a335592793cb83a738af412fef4", "html_url": "https://github.com/es6/es6.github.io/commit/410d1954b3319a335592793cb83a738af412fef4"}], "commit": {"committer": {"date": "2016-08-11T13:39:23Z", "name": "Michael[tm] Smith", "email": "mike@w3.org"}, "author": {"date": "2016-08-11T13:39:23Z", "name": "Kevin Gibbons", "email": "bakkot@gmail.com"}, "url": "https://api.github.com/repos/es6/es6.github.io/git/commits/14fd4a7f2e7e13605d30aa1f6139eac27f76d98e", "tree": {"url": "https://api.github.com/repos/es6/es6.github.io/git/trees/750dbd6b932d9c0055bff794f592097479c6f78c", "sha": "750dbd6b932d9c0055bff794f592097479c6f78c"}, "comment_count": 0, "message": "ES6 is no longer the latest spec (#2)"}}, "last_commit": {"committer": {"following_url": "https://api.github.com/users/sideshowbarker/following{/other_user}", "events_url": "https://api.github.com/users/sideshowbarker/events{/privacy}", "organizations_url": "https://api.github.com/users/sideshowbarker/orgs", "url": "https://api.github.com/users/sideshowbarker", "gists_url": "https://api.github.com/users/sideshowbarker/gists{/gist_id}", "html_url": "https://github.com/sideshowbarker", "subscriptions_url": "https://api.github.com/users/sideshowbarker/subscriptions", "avatar_url": "https://avatars.githubusercontent.com/u/194984?v=3", "repos_url": "https://api.github.com/users/sideshowbarker/repos", "received_events_url": "https://api.github.com/users/sideshowbarker/received_events", "gravatar_id": "", "starred_url": "https://api.github.com/users/sideshowbarker/starred{/owner}{/repo}", "site_admin": false, "login": "sideshowbarker", "type": "User", "id": 194984, "followers_url": "https://api.github.com/users/sideshowbarker/followers"}, "author": {"following_url": "https://api.github.com/users/sideshowbarker/following{/other_user}", "events_url": "https://api.github.com/users/sideshowbarker/events{/privacy}", "organizations_url": "https://api.github.com/users/sideshowbarker/orgs", "url": "https://api.github.com/users/sideshowbarker", "gists_url": "https://api.github.com/users/sideshowbarker/gists{/gist_id}", "html_url": "https://github.com/sideshowbarker", "subscriptions_url": "https://api.github.com/users/sideshowbarker/subscriptions", "avatar_url": "https://avatars.githubusercontent.com/u/194984?v=3", "repos_url": "https://api.github.com/users/sideshowbarker/repos", "received_events_url": "https://api.github.com/users/sideshowbarker/received_events", "gravatar_id": "", "starred_url": "https://api.github.com/users/sideshowbarker/starred{/owner}{/repo}", "site_admin": false, "login": "sideshowbarker", "type": "User", "id": 194984, "followers_url": "https://api.github.com/users/sideshowbarker/followers"}, "url": "https://api.github.com/repos/es6/es6.github.io/commits/c57d8c01ca6a5a2c6d47e1840a660e793394717b", "comments_url": "https://api.github.com/repos/es6/es6.github.io/commits/c57d8c01ca6a5a2c6d47e1840a660e793394717b/comments", "html_url": "https://github.com/es6/es6.github.io/commit/c57d8c01ca6a5a2c6d47e1840a660e793394717b", "sha": "c57d8c01ca6a5a2c6d47e1840a660e793394717b", "parents": [], "commit": {"committer": {"date": "2011-01-16T06:18:58Z", "name": "Michael(tm) Smith", "email": "mike@w3.org"}, "author": {"date": "2011-01-16T06:18:58Z", "name": "Michael(tm) Smith", "email": "mike@w3.org"}, "url": "https://api.github.com/repos/es6/es6.github.io/git/commits/c57d8c01ca6a5a2c6d47e1840a660e793394717b", "tree": {"url": "https://api.github.com/repos/es6/es6.github.io/git/trees/1db9374fdc16abca4fbe259d271c06ee0da88ac4", "sha": "1db9374fdc16abca4fbe259d271c06ee0da88ac4"}, "comment_count": 0, "message": "new"}}, "commits_count": 28}