{"first_commit": {"committer": {"following_url": "https://api.github.com/users/gvwilson/following{/other_user}", "events_url": "https://api.github.com/users/gvwilson/events{/privacy}", "organizations_url": "https://api.github.com/users/gvwilson/orgs", "url": "https://api.github.com/users/gvwilson", "gists_url": "https://api.github.com/users/gvwilson/gists{/gist_id}", "html_url": "https://github.com/gvwilson", "subscriptions_url": "https://api.github.com/users/gvwilson/subscriptions", "avatar_url": "https://avatars.githubusercontent.com/u/911566?v=3", "repos_url": "https://api.github.com/users/gvwilson/repos", "received_events_url": "https://api.github.com/users/gvwilson/received_events", "gravatar_id": "", "starred_url": "https://api.github.com/users/gvwilson/starred{/owner}{/repo}", "site_admin": false, "login": "gvwilson", "type": "User", "id": 911566, "followers_url": "https://api.github.com/users/gvwilson/followers"}, "author": {"following_url": "https://api.github.com/users/gvwilson/following{/other_user}", "events_url": "https://api.github.com/users/gvwilson/events{/privacy}", "organizations_url": "https://api.github.com/users/gvwilson/orgs", "url": "https://api.github.com/users/gvwilson", "gists_url": "https://api.github.com/users/gvwilson/gists{/gist_id}", "html_url": "https://github.com/gvwilson", "subscriptions_url": "https://api.github.com/users/gvwilson/subscriptions", "avatar_url": "https://avatars.githubusercontent.com/u/911566?v=3", "repos_url": "https://api.github.com/users/gvwilson/repos", "received_events_url": "https://api.github.com/users/gvwilson/received_events", "gravatar_id": "", "starred_url": "https://api.github.com/users/gvwilson/starred{/owner}{/repo}", "site_admin": false, "login": "gvwilson", "type": "User", "id": 911566, "followers_url": "https://api.github.com/users/gvwilson/followers"}, "url": "https://api.github.com/repos/swcarpentry/training-course/commits/298c305670b72b6a6d92f1dee704e25002e47a61", "comments_url": "https://api.github.com/repos/swcarpentry/training-course/commits/298c305670b72b6a6d92f1dee704e25002e47a61/comments", "html_url": "https://github.com/swcarpentry/training-course/commit/298c305670b72b6a6d92f1dee704e25002e47a61", "sha": "298c305670b72b6a6d92f1dee704e25002e47a61", "parents": [{"url": "https://api.github.com/repos/swcarpentry/training-course/commits/40944c8a9447a9ec2f1f824ebafb4c433a2133b3", "sha": "40944c8a9447a9ec2f1f824ebafb4c433a2133b3", "html_url": "https://github.com/swcarpentry/training-course/commit/40944c8a9447a9ec2f1f824ebafb4c433a2133b3"}], "commit": {"committer": {"date": "2016-08-02T22:01:36Z", "name": "Greg Wilson", "email": "gvwilson@third-bit.com"}, "author": {"date": "2016-08-02T22:01:36Z", "name": "Greg Wilson", "email": "gvwilson@third-bit.com"}, "url": "https://api.github.com/repos/swcarpentry/training-course/git/commits/298c305670b72b6a6d92f1dee704e25002e47a61", "tree": {"url": "https://api.github.com/repos/swcarpentry/training-course/git/trees/3f893d1089e8d6d7c7cd6f436caaa393a763e230", "sha": "3f893d1089e8d6d7c7cd6f436caaa393a763e230"}, "comment_count": 0, "message": "Removing CNAME (going to point another directory here)"}}, "last_commit": {"committer": {"following_url": "https://api.github.com/users/andreabedini/following{/other_user}", "events_url": "https://api.github.com/users/andreabedini/events{/privacy}", "organizations_url": "https://api.github.com/users/andreabedini/orgs", "url": "https://api.github.com/users/andreabedini", "gists_url": "https://api.github.com/users/andreabedini/gists{/gist_id}", "html_url": "https://github.com/andreabedini", "subscriptions_url": "https://api.github.com/users/andreabedini/subscriptions", "avatar_url": "https://avatars.githubusercontent.com/u/69135?v=3", "repos_url": "https://api.github.com/users/andreabedini/repos", "received_events_url": "https://api.github.com/users/andreabedini/received_events", "gravatar_id": "", "starred_url": "https://api.github.com/users/andreabedini/starred{/owner}{/repo}", "site_admin": false, "login": "andreabedini", "type": "User", "id": 69135, "followers_url": "https://api.github.com/users/andreabedini/followers"}, "author": {"following_url": "https://api.github.com/users/andreabedini/following{/other_user}", "events_url": "https://api.github.com/users/andreabedini/events{/privacy}", "organizations_url": "https://api.github.com/users/andreabedini/orgs", "url": "https://api.github.com/users/andreabedini", "gists_url": "https://api.github.com/users/andreabedini/gists{/gist_id}", "html_url": "https://github.com/andreabedini", "subscriptions_url": "https://api.github.com/users/andreabedini/subscriptions", "avatar_url": "https://avatars.githubusercontent.com/u/69135?v=3", "repos_url": "https://api.github.com/users/andreabedini/repos", "received_events_url": "https://api.github.com/users/andreabedini/received_events", "gravatar_id": "", "starred_url": "https://api.github.com/users/andreabedini/starred{/owner}{/repo}", "site_admin": false, "login": "andreabedini", "type": "User", "id": 69135, "followers_url": "https://api.github.com/users/andreabedini/followers"}, "url": "https://api.github.com/repos/swcarpentry/training-course/commits/5a87256546e392982182f092fcddc6a7a19124b6", "comments_url": "https://api.github.com/repos/swcarpentry/training-course/commits/5a87256546e392982182f092fcddc6a7a19124b6/comments", "html_url": "https://github.com/swcarpentry/training-course/commit/5a87256546e392982182f092fcddc6a7a19124b6", "sha": "5a87256546e392982182f092fcddc6a7a19124b6", "parents": [], "commit": {"committer": {"date": "2014-11-24T04:53:23Z", "name": "Andrea Bedini", "email": "abedini@ms.unimelb.edu.au"}, "author": {"date": "2014-11-24T04:53:09Z", "name": "Andrea Bedini", "email": "abedini@ms.unimelb.edu.au"}, "url": "https://api.github.com/repos/swcarpentry/training-course/git/commits/5a87256546e392982182f092fcddc6a7a19124b6", "tree": {"url": "https://api.github.com/repos/swcarpentry/training-course/git/trees/362ea669350b1cdfd5c2641193ddc596f69ba754", "sha": "362ea669350b1cdfd5c2641193ddc596f69ba754"}, "comment_count": 0, "message": "Initial commit"}}, "commits_count": 1499}