[{"name": ".project", "url": "https://api.github.com/repos/zptcsoft/zptcsoft.github.io/contents/.project?ref=master", "html_url": "https://github.com/zptcsoft/zptcsoft.github.io/blob/master/.project", "download_url": "https://raw.githubusercontent.com/zptcsoft/zptcsoft.github.io/master/.project", "sha": "4f9de1e2c87f43d771a91e1ff784321b1c003b5d", "_links": {"self": "https://api.github.com/repos/zptcsoft/zptcsoft.github.io/contents/.project?ref=master", "git": "https://api.github.com/repos/zptcsoft/zptcsoft.github.io/git/blobs/4f9de1e2c87f43d771a91e1ff784321b1c003b5d", "html": "https://github.com/zptcsoft/zptcsoft.github.io/blob/master/.project"}, "git_url": "https://api.github.com/repos/zptcsoft/zptcsoft.github.io/git/blobs/4f9de1e2c87f43d771a91e1ff784321b1c003b5d", "path": ".project", "type": "file", "size": 377}, {"name": "README.md", "url": "https://api.github.com/repos/zptcsoft/zptcsoft.github.io/contents/README.md?ref=master", "html_url": "https://github.com/zptcsoft/zptcsoft.github.io/blob/master/README.md", "download_url": "https://raw.githubusercontent.com/zptcsoft/zptcsoft.github.io/master/README.md", "sha": "358740ecebd79f9f3e9017f52fe4e72ecbbb0809", "_links": {"self": "https://api.github.com/repos/zptcsoft/zptcsoft.github.io/contents/README.md?ref=master", "git": "https://api.github.com/repos/zptcsoft/zptcsoft.github.io/git/blobs/358740ecebd79f9f3e9017f52fe4e72ecbbb0809", "html": "https://github.com/zptcsoft/zptcsoft.github.io/blob/master/README.md"}, "git_url": "https://api.github.com/repos/zptcsoft/zptcsoft.github.io/git/blobs/358740ecebd79f9f3e9017f52fe4e72ecbbb0809", "path": "README.md", "type": "file", "size": 16015}, {"name": "demo", "url": "https://api.github.com/repos/zptcsoft/zptcsoft.github.io/contents/demo?ref=master", "html_url": "https://github.com/zptcsoft/zptcsoft.github.io/tree/master/demo", "download_url": null, "sha": "b93cf82a10c8ddeb60c8734b84cddd37196557ca", "_links": {"self": "https://api.github.com/repos/zptcsoft/zptcsoft.github.io/contents/demo?ref=master", "git": "https://api.github.com/repos/zptcsoft/zptcsoft.github.io/git/trees/b93cf82a10c8ddeb60c8734b84cddd37196557ca", "html": "https://github.com/zptcsoft/zptcsoft.github.io/tree/master/demo"}, "git_url": "https://api.github.com/repos/zptcsoft/zptcsoft.github.io/git/trees/b93cf82a10c8ddeb60c8734b84cddd37196557ca", "path": "demo", "type": "dir", "size": 0}, {"name": "doc", "url": "https://api.github.com/repos/zptcsoft/zptcsoft.github.io/contents/doc?ref=master", "html_url": "https://github.com/zptcsoft/zptcsoft.github.io/tree/master/doc", "download_url": null, "sha": "0be3373abc20701b37e3edda5bbc587d4af61bcf", "_links": {"self": "https://api.github.com/repos/zptcsoft/zptcsoft.github.io/contents/doc?ref=master", "git": "https://api.github.com/repos/zptcsoft/zptcsoft.github.io/git/trees/0be3373abc20701b37e3edda5bbc587d4af61bcf", "html": "https://github.com/zptcsoft/zptcsoft.github.io/tree/master/doc"}, "git_url": "https://api.github.com/repos/zptcsoft/zptcsoft.github.io/git/trees/0be3373abc20701b37e3edda5bbc587d4af61bcf", "path": "doc", "type": "dir", "size": 0}, {"name": "index.html", "url": "https://api.github.com/repos/zptcsoft/zptcsoft.github.io/contents/index.html?ref=master", "html_url": "https://github.com/zptcsoft/zptcsoft.github.io/blob/master/index.html", "download_url": "https://raw.githubusercontent.com/zptcsoft/zptcsoft.github.io/master/index.html", "sha": "bdc6296e9f9fbbf510b85f8c4b9d776c256cb796", "_links": {"self": "https://api.github.com/repos/zptcsoft/zptcsoft.github.io/contents/index.html?ref=master", "git": "https://api.github.com/repos/zptcsoft/zptcsoft.github.io/git/blobs/bdc6296e9f9fbbf510b85f8c4b9d776c256cb796", "html": "https://github.com/zptcsoft/zptcsoft.github.io/blob/master/index.html"}, "git_url": "https://api.github.com/repos/zptcsoft/zptcsoft.github.io/git/blobs/bdc6296e9f9fbbf510b85f8c4b9d776c256cb796", "path": "index.html", "type": "file", "size": 252}, {"name": "pdf", "url": "https://api.github.com/repos/zptcsoft/zptcsoft.github.io/contents/pdf?ref=master", "html_url": "https://github.com/zptcsoft/zptcsoft.github.io/tree/master/pdf", "download_url": null, "sha": "2dab3a4d505d81c76b3ca2f78b1811c6bcb2f774", "_links": {"self": "https://api.github.com/repos/zptcsoft/zptcsoft.github.io/contents/pdf?ref=master", "git": "https://api.github.com/repos/zptcsoft/zptcsoft.github.io/git/trees/2dab3a4d505d81c76b3ca2f78b1811c6bcb2f774", "html": "https://github.com/zptcsoft/zptcsoft.github.io/tree/master/pdf"}, "git_url": "https://api.github.com/repos/zptcsoft/zptcsoft.github.io/git/trees/2dab3a4d505d81c76b3ca2f78b1811c6bcb2f774", "path": "pdf", "type": "dir", "size": 0}, {"name": "ppt", "url": "https://api.github.com/repos/zptcsoft/zptcsoft.github.io/contents/ppt?ref=master", "html_url": "https://github.com/zptcsoft/zptcsoft.github.io/tree/master/ppt", "download_url": null, "sha": "c730e520d3ef4eca4ada3c61539fd1a30da19a5f", "_links": {"self": "https://api.github.com/repos/zptcsoft/zptcsoft.github.io/contents/ppt?ref=master", "git": "https://api.github.com/repos/zptcsoft/zptcsoft.github.io/git/trees/c730e520d3ef4eca4ada3c61539fd1a30da19a5f", "html": "https://github.com/zptcsoft/zptcsoft.github.io/tree/master/ppt"}, "git_url": "https://api.github.com/repos/zptcsoft/zptcsoft.github.io/git/trees/c730e520d3ef4eca4ada3c61539fd1a30da19a5f", "path": "ppt", "type": "dir", "size": 0}, {"name": "soft", "url": "https://api.github.com/repos/zptcsoft/zptcsoft.github.io/contents/soft?ref=master", "html_url": "https://github.com/zptcsoft/zptcsoft.github.io/tree/master/soft", "download_url": null, "sha": "97dc960e208d422bf4834a47964dec1e23c3748e", "_links": {"self": "https://api.github.com/repos/zptcsoft/zptcsoft.github.io/contents/soft?ref=master", "git": "https://api.github.com/repos/zptcsoft/zptcsoft.github.io/git/trees/97dc960e208d422bf4834a47964dec1e23c3748e", "html": "https://github.com/zptcsoft/zptcsoft.github.io/tree/master/soft"}, "git_url": "https://api.github.com/repos/zptcsoft/zptcsoft.github.io/git/trees/97dc960e208d422bf4834a47964dec1e23c3748e", "path": "soft", "type": "dir", "size": 0}, {"name": "\u65b0\u5efa\u6587\u672c\u6587\u6863.txt", "url": "https://api.github.com/repos/zptcsoft/zptcsoft.github.io/contents/%E6%96%B0%E5%BB%BA%E6%96%87%E6%9C%AC%E6%96%87%E6%A1%A3.txt?ref=master", "html_url": "https://github.com/zptcsoft/zptcsoft.github.io/blob/master/%E6%96%B0%E5%BB%BA%E6%96%87%E6%9C%AC%E6%96%87%E6%A1%A3.txt", "download_url": "https://raw.githubusercontent.com/zptcsoft/zptcsoft.github.io/master/%E6%96%B0%E5%BB%BA%E6%96%87%E6%9C%AC%E6%96%87%E6%A1%A3.txt", "sha": "e69de29bb2d1d6434b8b29ae775ad8c2e48c5391", "_links": {"self": "https://api.github.com/repos/zptcsoft/zptcsoft.github.io/contents/%E6%96%B0%E5%BB%BA%E6%96%87%E6%9C%AC%E6%96%87%E6%A1%A3.txt?ref=master", "git": "https://api.github.com/repos/zptcsoft/zptcsoft.github.io/git/blobs/e69de29bb2d1d6434b8b29ae775ad8c2e48c5391", "html": "https://github.com/zptcsoft/zptcsoft.github.io/blob/master/%E6%96%B0%E5%BB%BA%E6%96%87%E6%9C%AC%E6%96%87%E6%A1%A3.txt"}, "git_url": "https://api.github.com/repos/zptcsoft/zptcsoft.github.io/git/blobs/e69de29bb2d1d6434b8b29ae775ad8c2e48c5391", "path": "\u65b0\u5efa\u6587\u672c\u6587\u6863.txt", "type": "file", "size": 0}]